qa_qc_check/__init__.py
qa_qc_check/controller/__init__.py
qa_qc_check/controller/checks.json
qa_qc_check/controller/meta_data.py
qa_qc_check/controller/meta_data_extractor.py
qa_qc_check/controller/meta_data_validator.py
qa_qc_check/controller/metadata_model.py
qa_qc_check/controller/qa_qc.py
qa_qc_check/tests/__init__.py
qa_qc_check/tests/test_meta_data_extractor.py
satelite/__init__.py
satelite/config.py
satelite/sentinel2/__init__.py
satelite/sentinel2/fetch_unique_tile_date.py
satelite/sentinel2/fetch_unique_tile_date_pystac.py
satelite/sentinel2/get_tiles.py
satelite/tests/__init__.py
satelite/tests/conftest.py
satelite/tests/sentinel2/__init__.py
satelite/tests/sentinel2/test_fetch_unique_tile_date.py
satelite/tests/sentinel2/test_fetch_unique_tile_date_pystac.py
satelite/tests/sentinel2/test_get_tile.py
test_core-0.0.2.dist-info/LICENCE.txt
test_core-0.0.2.dist-info/METADATA
test_core-0.0.2.dist-info/WHEEL
test_core-0.0.2.dist-info/top_level.txt
test_core-0.0.2.dist-info/RECORD
